py2gui/game_example.py
py2gui/py2gui.py
py2gui/test.py
py2gui-0.1.0.dist-info/licenses/LICENSE
py2gui-0.1.0.dist-info/METADATA
py2gui-0.1.0.dist-info/WHEEL
py2gui-0.1.0.dist-info/top_level.txt
py2gui-0.1.0.dist-info/RECORD
