Metadata-Version: 2.4
Name: py2gui
Version: 0.1.0
Summary: Simple python to GUI (Tkinter) tool
Author: Andy
Requires-Python: >=3.8
License-File: LICENSE
Dynamic: license-file
